extcats/CatalogPusher.py
extcats/CatalogQuery.py
extcats/GwPusher.py
extcats/GwQuery.py
extcats/__init__.py
extcats/catquery_utils.py
extcats/testdata.py
extcats-2.5.0.dist-info/LICENSE
extcats-2.5.0.dist-info/METADATA
extcats-2.5.0.dist-info/WHEEL
extcats-2.5.0.dist-info/RECORD
