Metadata-Version: 2.1
Name: extcats
Version: 2.5.0
Summary: Tools to organize and query astronomical catalogs
Home-page: https://github.com/AmpelProject/extcats
License: MIT
Author: Matteo Giomi
Author-email: matteo.giomi@desy.de
Maintainer: Jakob van Santen
Maintainer-email: jakob.van.santen@desy.de
Requires-Python: >=3.9,<4.0
Classifier: License :: OSI Approved :: MIT License
Classifier: Programming Language :: Python :: 3
Classifier: Programming Language :: Python :: 3.9
Classifier: Programming Language :: Python :: 3.10
Classifier: Programming Language :: Python :: 3.11
Classifier: Programming Language :: Python :: 3.12
Provides-Extra: ingest
Requires-Dist: astropy (>=4.2)
Requires-Dist: healpy (>=1.14.0,<2.0.0)
Requires-Dist: pandas (>=1.2) ; extra == "ingest"
Requires-Dist: pymongo (>=3.7,<5.0)
Requires-Dist: tqdm (>=4.58.0,<5.0.0) ; extra == "ingest"
Project-URL: Repository, https://github.com/AmpelProject/extcats
